performanceanalytics/__init__.py
performanceanalytics/drawdowns.py
performanceanalytics/seriesholder.py
performanceanalytics/statistics.py
performanceanalytics/charts/__init__.py
performanceanalytics/charts/boxplot.py
performanceanalytics/charts/performance_histogram.py
performanceanalytics/charts/performance_summary.py
performanceanalytics/charts/riskreturnscatter.py
performanceanalytics/charts/rolling_performance.py
performanceanalytics/charts/rolling_regression.py
performanceanalytics/table/__init__.py
performanceanalytics/table/table.py
tests/__init__.py
tests/performanceanalytics/__init__.py
tests/performanceanalytics/conftest.py
tests/performanceanalytics/test_seriesholder.py
tests/performanceanalytics/test_statistics.py
tests/performanceanalytics/test_table.py
PerformanceAnalytics-0.14.dist-info/LICENSE.txt
PerformanceAnalytics-0.14.dist-info/METADATA
PerformanceAnalytics-0.14.dist-info/WHEEL
PerformanceAnalytics-0.14.dist-info/top_level.txt
PerformanceAnalytics-0.14.dist-info/RECORD
