Metadata-Version: 2.1
Name: PerformanceAnalytics
Version: 0.14
Summary: A port of R's performance analytics to python
Home-page: https://github.com/justthetips/PerformanceAnalytics
Author: Jacob Bourne
Author-email: jacob.bourne@gmail.com
License: MIT
Platform: UNKNOWN
